{
"LogonWindow_ConnectingAccount": "Conectando cuenta...",
"LogonWindow_ConnectWallet": "Conectar billetera",
"LogonWindow_RegisterWallet": "Crear o importar billetera",
"LogonWindow_SearchingConnection": "Buscando conexión...",
"LogonWindow_Title": "Bienvenido a la billetera XDAGJ (Ver %s)",
"LogonWindow_AppearanceSetting": "Configuración de apariencia",
"LogonWindow_SelectWalletTitle": "Seleccione tipo de billetera",
"LogonWindow_SelectWalletType": "Tipo de billetera",
"LogonWindow_WalletType_NonMnemonic": "No mnemónica",
"LogonWindow_WalletType_Mnemonic": "Mnemónica",
"LogonWindow_Import_NonMnemonic": "Importar no mnemónica",
"LogonWindow_Import_Mnemonic": "Importar mnemónica",
"LogonWindow_Create_Mnemonic": "Crear mnemónica",
"Common_ConfirmTitle": "Confirmar",
"Common_MessageTitle": "Mensaje",
"Message_PasswordIncorrect": "La contraseña es incorrecta",
"PasswordWindow_Enter": "Ingresar",
"PasswordWindow_InputPassword": "Ingresar contraseña:",
"PasswordWindow_RetypePassword": "Volver a ingresar contraseña:",
"PasswordWindow_SetPassword": "Establecer contraseña:",
"WalletState_ConnectedAndMining": "Conectado y minando",
"WalletState_ConnectedNetwork": "Conectado a la red",
"WalletState_ConnectedPool": "Conectado al grupo de minería",
"WalletState_ConnectingNetwork": "Conectando a la red...",
"WalletState_ConnectingPool": "Conectando al grupo de minería...",
"WalletState_Idle": "Inactivo",
"WalletState_LoadingBlocks": "Cargando bloques...",
"WalletState_None": "No existe",
"WalletState_Registering": "Registrando...",
"WalletState_Register_failed": "Falló al registrar la nueva billetera...",
"WalletState_ResettingEngine": "Reiniciando el motor...",
"WalletState_Stopped": "Detenido",
"WalletState_Synchronized": "Sincronizado",
"WalletState_Synchronizing": "Sincronizando...",
"WalletState_TransferPending": "Transferencia pendiente...",
"Common_Cancel": "Cancelar",
"LogonWindow_InitializeFailed": "Falló la inicialización:",
"LogonWindow_InitializingAccount": "Inicializando cuenta...",
"LogonWindow_InitializingElapsedTime": "Tiempo transcurrido:[%s](Necesita unos 5-10 minutos)",
"PasswordWindow_PasswordMismatch": "La contraseña no coincide con la\nanterior que ingresó.",
"TransferWindow_AccountFormatError": "El formato de la dirección de billetera es incorrecto.",
"TransferWindow_FromAddress": "Desde la dirección:",
"TransferWindow_AddressTitle": "A la dirección:",
"TransferWindow_AmountFormatError": "El monto debe ser un número positivo.",
"TransferWindow_CommitFailed": "Falló la transacción:",
"TransferWindow_CommitSuccess": "La transferencia se ha realizado. Por favor, espere un momento para que se complete.",
"TransferWindow_CommittingTransaction": "Cometiendo transacción...",
"TransferWindow_ConfirmTransfer": "¿Estás seguro de que quieres transferir %s XDAGs\n a [%s]?",
"TransferWindow_ConfirmDelete": "¿Estás seguro de que quieres eliminar [%s]？",
"TransferWindow_InsufficientAmount": "El saldo de tu billetera no es suficiente.",
"TransferWindow_Title": "Transferir XDAG a dirección",
"TransferWindow_TransferTitle": "Transferir",
"TransferWindow_MostRecently": "Direcciones transferidas recientemente:",
"WalletWindow_AddressCopied": "La dirección de la billetera se ha copiado al portapapeles.",
"WalletWindow_CopyAddress": "Copiar dirección de la billetera",
"WalletWindow_AddressTitle": "Dirección:",
"WalletWindow_BalanceTitle": "Saldo:",
"WalletWindow_StatusTitle": "Estado:",
"WalletWindow_Title": "Billetera XDag",
"WalletWindow_TransferTitle": "Generar transacción",
"Common_Confirm": "Confirmar",
"SettingsWindow_ChooseLanguage": "Elegir idioma",
"SettingsWindow_Title": "Configuración",
"WalletWindow_TabAccount": "Cuenta",
"WalletWindow_TabHistory": "Transacciones",
"WalletWindow_TabDonate": "Donar",
"WalletWindow_TabTransfer": "Transferir",
"WalletWindow_TabSettings": "Configuración",
"WalletWindow_TabAbout": "Acerca de",
"LogonWindow_NoPoolAddress": "\nLa lectura de PoolAddress desde el archivo de configuración falló. \nPor favor, verifica que la dirección del pool se haya establecido correctamente en wallet-config.json bajo Opciones.\n",
"WalletWindow_HistoryBusy": "Cargando datos de historial...",
"WalletWindow_HistoryError": "Error al cargar los datos de historial",
"WalletWindow_HistoryColumns_Amount": "Cantidad",
"WalletWindow_HistoryColumns_BlockAddress": "Dirección de bloque",
"WalletWindow_HistoryColumns_Direction": "Dirección",
"WalletWindow_HistoryColumns_PartnerAddress": "Dirección de transacción",
"WalletWindow_HistoryColumns_Status": "Estado",
"WalletWindow_HistoryColumns_TimeStamp": "Fecha y hora",
"WalletWindow_History_Input": "Entrada",
"WalletWindow_History_Output": "Salida",
"WalletWindow_History_Filter": "Filtro",
"WalletWindow_Filter_AmountFrom": "Cantidad desde",
"WalletWindow_Filter_AmountTo": "Cantidad hasta",
"WalletWindow_Filter_DateFrom": "Fecha desde",
"WalletWindow_Filter_DateTo": "Fecha hasta",
"WalletWindow_Filter_NoResult": "No hay resultados.",
"WalletWindow_Filter_AllDirect": "Entrada y salida",
"WalletWindow_Filter_Week": "Última semana",
"WalletWindow_Filter_Month": "Último mes",
"WalletWindow_Filter_Year": "Último año",
"WalletWindow_Filter_Remember": "Recuerda:",
"WalletWindow_Filter_RemOption": "Recordar como filtro predeterminado",
"WalletWindow_VersionLabel": "Versión %s",
"WalletWindow_Transfer_Amount": "Cantidad:",
"WalletWindow_Transfer_ToAddress": "A dirección:",
"TransferWindow_RemarkFormatError": "El formato de la observación es incorrecto. Debe tener un máximo de 32 caracteres",
"WalletWindow_Transfer_Remark": "Observación:",
"WalletWindow_HistoryColumns_Remark": "Observación",
"Dark": "Oscuro",
"Light": "Claro",
"WalletImport_WalletNotExist": "Archivos de billetera no existen",
"WalletImport_FilesCopyFailed": "Fallo al copiar archivos de billetera",
"WalletExport_File_Failed": "Exportación de mnemónicos fallida",
"WalletExport_File_Success": "Exportación de mnemónicos exitosa",
"WalletCreate_FilesFailed": "Fallo al crear archivos de billetera",
"Wallet_CreateOrImport": "Por favor elija, crear o importar una billetera?",
"Wallet_Choice": "Elección",
"Wallet_Create": "Crear",
"Wallet_Import": "Importar",
"Wallet_Export": "Exportar mnemónicos",
"Display_Mnemonic": "Mostrar mnemónicos",
"Rpc_Get_Balance_fail": "Fallo al obtener el saldo de la cuenta"
}